mubody/__init__.py
mubody/constants.py
mubody/mission.py
mubody/numeric.py
mubody/testing.py
mubody/utilities.py
mubody/algorithms/__init__.py
mubody/algorithms/orbital.py
mubody/coordinates/__init__.py
mubody/coordinates/frames.py
mubody/core/__init__.py
mubody/core/ephemeris.py
mubody/core/kepler.py
mubody/core/orbit.py
mubody/core/perturbations.py
mubody/core/physic.py
mubody/core/rnbp.py
mubody/core/satellite.py
mubody/core/universe.py
mubody/postprocessing/__init__.py
mubody/postprocessing/pdata.py
mubody/postprocessing/pgraph.py
mubody/tests/__init__.py
mubody/tests/test_missions.py
mubody/tests/test_physics.py
mubody/tests/test_rnbp.py
mubody/tests/test_save_load.py
mubody/tests/test_utilities.py
mubody/utilities/__init__.py
mubody/utilities/eclipse.py
mubody/utilities/external_apis.py
mubody/utilities/io.py
mubody/utilities/math.py
mubody/utilities/rotations.py
mubody/utilities/time.py
mubody-0.0.2.dist-info/AUTHORS.rst
mubody-0.0.2.dist-info/LICENSE.txt
mubody-0.0.2.dist-info/METADATA
mubody-0.0.2.dist-info/WHEEL
mubody-0.0.2.dist-info/top_level.txt
mubody-0.0.2.dist-info/RECORD
