Metadata-Version: 2.1
Name: mubody
Version: 0.0.2
Summary: Multi-body dynamics in libration points
Author-email: Juan Bermejo <juan.bermejo@protonmail.com>
License: The MIT License (MIT)
Project-URL: homepage, https://gitlab.com/mubody/mubody
Project-URL: documentation, https://mubody.readthedocs.io/
Project-URL: repository, https://gitlab.com/mubody/mubody
Project-URL: tracker, https://gitlab.com/mubody/mubody/-/issues
Keywords: libration points,nonkeplerian,multi-body dynamics,astrodynamics
Classifier: License :: OSI Approved :: MIT License
Classifier: Intended Audience :: Education
Classifier: Intended Audience :: Science/Research
Classifier: Operating System :: OS Independent
Classifier: Programming Language :: Python :: 3
Classifier: Topic :: Scientific/Engineering
Requires-Python: >=3.8
License-File: LICENSE.txt
License-File: AUTHORS.rst
Requires-Dist: numpy
Requires-Dist: scipy
Requires-Dist: pandas
Requires-Dist: matplotlib
Requires-Dist: tqdm
Requires-Dist: astropy
Requires-Dist: spiceypy
Requires-Dist: numba
Requires-Dist: requests
Provides-Extra: doc
Requires-Dist: sphinx ; extra == 'doc'
Requires-Dist: sphinx-rtd-theme ; extra == 'doc'
Requires-Dist: myst-parser ; extra == 'doc'
Provides-Extra: jupyter
Requires-Dist: notebook ; extra == 'jupyter'
Requires-Dist: ipywidgets >=7.6 ; extra == 'jupyter'
Provides-Extra: test
Requires-Dist: pytest ; extra == 'test'
Requires-Dist: flake8 ; extra == 'test'
Requires-Dist: black ; extra == 'test'
Requires-Dist: mypy ; extra == 'test'
